README.md
setup.py
privam/__init__.py
privam/privam_bot.py
privam.egg-info/PKG-INFO
privam.egg-info/SOURCES.txt
privam.egg-info/dependency_links.txt
privam.egg-info/requires.txt
privam.egg-info/top_level.txt