Metadata-Version: 2.1
Name: privam
Version: 1.0.5
